{"selector_chain_id_to_selector_chain_info": {"7431446039364": {"sortType": 1, "indexStart": 0, "inexistence": false, "needFindInPage": false, "selectors": [{"mode": "MODE_SELF_SATISFY", "props": {"selectedMatters": false, "classNameReg": "", "contentDescMatters": false, "clickableMatters": true, "textMatters": false, "checkedMatters": false, "shouldCheckable": false, "shouldSelected": false, "editableMatters": false, "textReg": "", "shouldScrollable": false, "contentDescReg": "", "classNameMatters": false, "shouldClickable": true, "checkableMatters": false, "resourceIdReg": "ensure", "subDistance": "*", "shouldChecked": false, "scrollableMatters": false, "resourceIdMatters": true, "shouldEditable": false}, "id": 1580877012524, "name": "AbsoluteNodeSelector"}], "indexEnd": null, "id": 7431446039364}, "9482126994458": {"sortType": 1, "indexStart": 0, "inexistence": false, "needFindInPage": true, "selectors": [{"mode": "MODE_SELF_SATISFY", "props": {"selectedMatters": false, "classNameReg": "", "contentDescMatters": false, "clickableMatters": false, "textMatters": false, "checkedMatters": false, "shouldCheckable": false, "shouldSelected": false, "editableMatters": false, "textReg": "", "shouldScrollable": false, "contentDescReg": "", "classNameMatters": false, "shouldClickable": false, "checkableMatters": false, "resourceIdReg": "^com.alipay.android.phone.mobilecommon.verifyidentity:id/message$", "subDistance": "*", "shouldChecked": false, "scrollableMatters": false, "resourceIdMatters": true, "shouldEditable": false}, "id": 1580876952502, "name": "AbsoluteNodeSelector"}], "indexEnd": null, "id": 9482126994458}, "1334205495332": {"sortType": 1, "indexStart": 0, "inexistence": false, "needFindInPage": false, "selectors": [{"mode": "MODE_SELF_SATISFY", "props": {"selectedMatters": false, "classNameReg": "", "contentDescMatters": false, "clickableMatters": true, "textMatters": false, "checkedMatters": false, "shouldCheckable": false, "shouldSelected": false, "editableMatters": false, "textReg": "", "shouldScrollable": false, "contentDescReg": "", "classNameMatters": false, "shouldClickable": true, "checkableMatters": false, "resourceIdReg": "cancel", "subDistance": "*", "shouldChecked": false, "scrollableMatters": false, "resourceIdMatters": true, "shouldEditable": false}, "id": 1580876990765, "name": "AbsoluteNodeSelector"}], "indexEnd": null, "id": 1334205495332}}, "vt_id_to_selector_chain_id": {"1583412229724": 7431446039364, "1578898539363": 1334205495332, "1578898484911": 9482126994458, "1581745802635": 1334205495332, "1578898552210": 7431446039364}, "vt_id_to_trans_info_list": {"1578898552210": [{"action_vt_id": 1578898552210, "para_desc": "\u4e0d\u53ef\u53d8-\u786e\u8ba4", "trans_res": [187], "para_vt_id": null, "action_type": "\u70b9\u51fb", "con_id": "1583412221239", "next_trans_con_id": -1}], "1578898539363": [{"action_vt_id": 1578898539363, "para_desc": "\u4e0d\u53ef\u53d8-\u5176\u4ed6\u9a8c\u8bc1\u65b9\u5f0f", "trans_res": [28], "para_vt_id": null, "action_type": "\u70b9\u51fb", "con_id": "1581745791556", "next_trans_con_id": -1}]}, "node_path_id_to_vt_id": {"android.widget.FrameLayout|0;android.widget.FrameLayout|0;android.widget.FrameLayout|0;android.widget.RelativeLayout|1;android.widget.RelativeLayout|1;android.widget.Button": "1578898552210", "android.widget.FrameLayout|0;android.widget.FrameLayout|0;android.widget.FrameLayout|0;android.widget.RelativeLayout|1;android.widget.RelativeLayout|0;android.widget.Button": "1578898539363", "android.widget.FrameLayout|0;android.widget.FrameLayout|0;android.widget.FrameLayout|0;android.widget.RelativeLayout|0;android.widget.TextView": "1578898484911"}, "con_id_to_trans_info": {"1583412221239": {"action_vt_id": 1578898552210, "para_desc": "\u4e0d\u53ef\u53d8-\u786e\u8ba4", "trans_res": [187], "para_vt_id": null, "action_type": "\u70b9\u51fb", "con_id": "1583412221239", "next_trans_con_id": -1}, "1581745791556": {"action_vt_id": 1578898539363, "para_desc": "\u4e0d\u53ef\u53d8-\u5176\u4ed6\u9a8c\u8bc1\u65b9\u5f0f", "trans_res": [28], "para_vt_id": null, "action_type": "\u70b9\u51fb", "con_id": "1581745791556", "next_trans_con_id": -1}}}