{"selector_chain_id_to_selector_chain_info": {"6708136638210": {"sortType": 1, "indexStart": 0, "inexistence": false, "needFindInPage": false, "selectors": [{"mode": "MODE_SELF_SATISFY", "props": {"selectedMatters": false, "classNameReg": "Button", "contentDescMatters": false, "clickableMatters": true, "textMatters": true, "checkedMatters": false, "shouldCheckable": false, "shouldSelected": false, "editableMatters": false, "textReg": "^\u53d1\u9001$", "shouldScrollable": false, "contentDescReg": "", "classNameMatters": false, "shouldClickable": true, "checkableMatters": false, "resourceIdReg": "", "subDistance": "*", "shouldChecked": false, "scrollableMatters": false, "resourceIdMatters": false, "shouldEditable": false}, "id": 1590083286744, "name": "AbsoluteNodeSelector"}], "indexEnd": null, "id": 6708136638210}, "1404664386881": {"sortType": 1, "indexStart": 0, "inexistence": false, "needFindInPage": true, "selectors": [{"mode": "MODE_SELF_SATISFY", "props": {"selectedMatters": false, "classNameReg": "", "contentDescMatters": false, "clickableMatters": false, "textMatters": true, "checkedMatters": false, "shouldCheckable": false, "shouldSelected": false, "editableMatters": false, "textReg": "\u9a8c\u8bc1\u7533\u8bf7", "shouldScrollable": false, "contentDescReg": "", "classNameMatters": false, "shouldClickable": false, "checkableMatters": false, "resourceIdReg": "", "subDistance": "*", "shouldChecked": false, "scrollableMatters": false, "resourceIdMatters": false, "shouldEditable": false}, "id": 1590083241766, "name": "AbsoluteNodeSelector"}], "indexEnd": null, "id": 1404664386881}, "6901244336589": {"sortType": 1, "indexStart": 0, "inexistence": false, "needFindInPage": false, "selectors": [{"mode": "MODE_SELF_SATISFY", "props": {"selectedMatters": false, "classNameReg": "", "contentDescMatters": true, "clickableMatters": false, "textMatters": false, "checkedMatters": false, "shouldCheckable": false, "shouldSelected": false, "editableMatters": false, "textReg": "", "shouldScrollable": false, "contentDescReg": "\u8fd4\u56de", "classNameMatters": false, "shouldClickable": false, "checkableMatters": false, "resourceIdReg": "", "subDistance": "*", "shouldChecked": false, "scrollableMatters": false, "resourceIdMatters": false, "shouldEditable": false}, "id": 1590083254233, "name": "AbsoluteNodeSelector"}, {"mode": "MODE_FIRST_SATISFY_ANCESTOR", "props": {"selectedMatters": false, "classNameReg": "", "contentDescMatters": false, "clickableMatters": true, "textMatters": false, "checkedMatters": false, "shouldCheckable": false, "shouldSelected": false, "editableMatters": false, "textReg": "", "shouldScrollable": false, "contentDescReg": "", "classNameMatters": false, "shouldClickable": true, "checkableMatters": false, "resourceIdReg": "", "subDistance": "*", "shouldChecked": false, "scrollableMatters": false, "resourceIdMatters": false, "shouldEditable": false}, "id": 1590083273285, "name": "AbsoluteNodeSelector"}], "indexEnd": null, "id": 6901244336589}}, "vt_id_to_selector_chain_id": {"1590079415213": 6901244336589, "1590079469646": 6708136638210}, "vt_id_to_trans_info_list": {"1590079415213": [{"action_vt_id": 1590079415213, "para_desc": "\u4e0d\u53ef\u53d8-\u8fd4\u56de", "trans_res": [10], "para_vt_id": null, "action_type": "\u70b9\u51fb", "con_id": "1590079405161", "next_trans_con_id": -1}], "1590079469646": [{"action_vt_id": 1590079469646, "para_desc": "\u4e0d\u53ef\u53d8-\u53d1\u9001", "trans_res": [10], "para_vt_id": null, "action_type": "\u70b9\u51fb", "con_id": "1590079461878", "next_trans_con_id": -1}]}, "node_path_id_to_vt_id": {"android.widget.FrameLayout|0;android.widget.FrameLayout|0;android.widget.FrameLayout|0;android.widget.LinearLayout|0;android.widget.FrameLayout|0;android.view.ViewGroup|0;android.widget.FrameLayout|0;android.view.ViewGroup|1;android.support.v7.widget.LinearLayoutCompat|0;android.widget.LinearLayout|0;android.widget.Button": "1590079469646", "android.widget.FrameLayout|0;android.widget.FrameLayout|0;android.widget.FrameLayout|0;android.widget.LinearLayout|0;android.widget.FrameLayout|0;android.view.ViewGroup|0;android.widget.FrameLayout|0;android.view.ViewGroup|0;android.widget.LinearLayout|0;android.widget.LinearLayout": "1590079415213"}, "con_id_to_trans_info": {"1590079461878": {"action_vt_id": 1590079469646, "para_desc": "\u4e0d\u53ef\u53d8-\u53d1\u9001", "trans_res": [10], "para_vt_id": null, "action_type": "\u70b9\u51fb", "con_id": "1590079461878", "next_trans_con_id": -1}, "1590079405161": {"action_vt_id": 1590079415213, "para_desc": "\u4e0d\u53ef\u53d8-\u8fd4\u56de", "trans_res": [10], "para_vt_id": null, "action_type": "\u70b9\u51fb", "con_id": "1590079405161", "next_trans_con_id": -1}}}