{"@index": "0", "@text": "", "@resource-id": "", "@class": "android.widget.FrameLayout", "@package": "com.eg.android.AlipayGphone", "@content-desc": "", "@checkable": "false", "@checked": "false", "@clickable": "false", "@enabled": "true", "@focusable": "false", "@focused": "false", "@scrollable": "false", "@long-clickable": "false", "@password": "false", "@selected": "false", "@editable": "false", "@accessibilityFocused": "false", "@dismissable": "false", "@bounds": "[0,0][1080,2340]", "node": [{"@index": "0", "@text": "", "@resource-id": "", "@class": "android.widget.LinearLayout", "@package": "com.eg.android.AlipayGphone", "@content-desc": "", "@checkable": "false", "@checked": "false", "@clickable": "false", "@enabled": "true", "@focusable": "false", "@focused": "false", "@scrollable": "false", "@long-clickable": "false", "@password": "false", "@selected": "false", "@editable": "false", "@accessibilityFocused": "false", "@dismissable": "false", "@bounds": "[0,0][1080,2340]", "node": {"@index": "0", "@text": "", "@resource-id": "android:id/content", "@class": "android.widget.FrameLayout", "@package": "com.eg.android.AlipayGphone", "@content-desc": "", "@checkable": "false", "@checked": "false", "@clickable": "false", "@enabled": "true", "@focusable": "false", "@focused": "false", "@scrollable": "false", "@long-clickable": "false", "@password": "false", "@selected": "false", "@editable": "false", "@accessibilityFocused": "false", "@dismissable": "false", "@bounds": "[0,85][1080,2340]", "node": {"@index": "0", "@text": "", "@resource-id": "com.alipay.mobile.chatapp:id/chat_mainview", "@class": "android.widget.RelativeLayout", "@package": "com.eg.android.AlipayGphone", "@content-desc": "", "@checkable": "false", "@checked": "false", "@clickable": "false", "@enabled": "true", "@focusable": "false", "@focused": "false", "@scrollable": "false", "@long-clickable": "false", "@password": "false", "@selected": "false", "@editable": "false", "@accessibilityFocused": "false", "@dismissable": "false", "@bounds": "[0,85][1080,2340]", "node": [{"@index": "0", "@text": "", "@resource-id": "com.alipay.mobile.chatapp:id/chat_title_bar", "@class": "android.widget.RelativeLayout", "@package": "com.eg.android.AlipayGphone", "@content-desc": "", "@checkable": "false", "@checked": "false", "@clickable": "false", "@enabled": "true", "@focusable": "false", "@focused": "false", "@scrollable": "false", "@long-clickable": "false", "@password": "false", "@selected": "false", "@editable": "false", "@accessibilityFocused": "false", "@dismissable": "false", "@bounds": "[0,85][1080,228]", "node": {"@index": "0", "@text": "", "@resource-id": "com.alipay.mobile.antui:id/title_bar_kernel", "@class": "android.widget.RelativeLayout", "@package": "com.eg.android.AlipayGphone", "@content-desc": "", "@checkable": "false", "@checked": "false", "@clickable": "false", "@enabled": "true", "@focusable": "false", "@focused": "false", "@scrollable": "false", "@long-clickable": "false", "@password": "false", "@selected": "false", "@editable": "false", "@accessibilityFocused": "false", "@dismissable": "false", "@bounds": "[0,85][1080,228]", "node": {"@index": "0", "@text": "", "@resource-id": "com.alipay.mobile.antui:id/title_bar_horizon", "@class": "android.widget.LinearLayout", "@package": "com.eg.android.AlipayGphone", "@content-desc": "", "@checkable": "false", "@checked": "false", "@clickable": "false", "@enabled": "true", "@focusable": "false", "@focused": "false", "@scrollable": "false", "@long-clickable": "false", "@password": "false", "@selected": "false", "@editable": "false", "@accessibilityFocused": "false", "@dismissable": "false", "@bounds": "[0,85][1080,228]", "node": [{"@index": "0", "@text": "", "@resource-id": "com.alipay.mobile.antui:id/back_button", "@class": "android.widget.FrameLayout", "@package": "com.eg.android.AlipayGphone", "@content-desc": "\u8fd4\u56de", "@checkable": "false", "@checked": "false", "@clickable": "true", "@enabled": "true", "@focusable": "true", "@focused": "false", "@scrollable": "false", "@long-clickable": "false", "@password": "false", "@selected": "false", "@editable": "false", "@accessibilityFocused": "false", "@dismissable": "false", "@bounds": "[5,85][137,228]", "node": {"@index": "0", "@text": "", "@resource-id": "", "@class": "android.widget.ImageView", "@package": "com.eg.android.AlipayGphone", "@content-desc": "", "@checkable": "false", "@checked": "false", "@clickable": "false", "@enabled": "true", "@focusable": "false", "@focused": "false", "@scrollable": "false", "@long-clickable": "false", "@password": "false", "@selected": "false", "@editable": "false", "@accessibilityFocused": "false", "@dismissable": "false", "@bounds": "[5,85][137,228]"}}, {"@index": "1", "@text": "", "@resource-id": "com.alipay.mobile.antui:id/title_container", "@class": "android.widget.RelativeLayout", "@package": "com.eg.android.AlipayGphone", "@content-desc": "", "@checkable": "false", "@checked": "false", "@clickable": "false", "@enabled": "true", "@focusable": "false", "@focused": "false", "@scrollable": "false", "@long-clickable": "false", "@password": "false", "@selected": "false", "@editable": "false", "@accessibilityFocused": "false", "@dismissable": "false", "@bounds": "[137,85][822,228]", "node": {"@index": "0", "@text": "\u839c\u84dd", "@resource-id": "com.alipay.mobile.antui:id/title_text", "@class": "android.widget.TextView", "@package": "com.eg.android.AlipayGphone", "@content-desc": "", "@checkable": "false", "@checked": "false", "@clickable": "false", "@enabled": "true", "@focusable": "false", "@focused": "false", "@scrollable": "false", "@long-clickable": "false", "@password": "false", "@selected": "false", "@editable": "false", "@accessibilityFocused": "false", "@dismissable": "false", "@bounds": "[137,120][245,192]"}}, {"@index": "2", "@text": "", "@resource-id": "com.alipay.mobile.antui:id/right_container_1", "@class": "android.widget.RelativeLayout", "@package": "com.eg.android.AlipayGphone", "@content-desc": "\u67e5\u770b\u8f6c\u8d26\u8bb0\u5f55", "@checkable": "false", "@checked": "false", "@clickable": "true", "@enabled": "true", "@focusable": "true", "@focused": "false", "@scrollable": "false", "@long-clickable": "false", "@password": "false", "@selected": "false", "@editable": "false", "@accessibilityFocused": "false", "@dismissable": "false", "@bounds": "[822,85][952,228]", "node": [{"@index": "0", "@text": "", "@resource-id": "com.alipay.mobile.antui:id/left_text", "@class": "android.widget.FrameLayout", "@package": "com.eg.android.AlipayGphone", "@content-desc": "", "@checkable": "false", "@checked": "false", "@clickable": "false", "@enabled": "true", "@focusable": "false", "@focused": "false", "@scrollable": "false", "@long-clickable": "false", "@password": "false", "@selected": "false", "@editable": "false", "@accessibilityFocused": "false", "@dismissable": "false", "@bounds": "[834,85][904,228]", "node": {"@index": "0", "@text": "", "@resource-id": "", "@class": "android.widget.ImageView", "@package": "com.eg.android.AlipayGphone", "@content-desc": "", "@checkable": "false", "@checked": "false", "@clickable": "false", "@enabled": "true", "@focusable": "false", "@focused": "false", "@scrollable": "false", "@long-clickable": "false", "@password": "false", "@selected": "false", "@editable": "false", "@accessibilityFocused": "false", "@dismissable": "false", "@bounds": "[834,85][904,228]"}}, {"@index": "1", "@text": "", "@resource-id": "", "@class": "android.view.View", "@package": "com.eg.android.AlipayGphone", "@content-desc": "", "@checkable": "false", "@checked": "false", "@clickable": "false", "@enabled": "true", "@focusable": "false", "@focused": "false", "@scrollable": "false", "@long-clickable": "false", "@password": "false", "@selected": "false", "@editable": "false", "@accessibilityFocused": "false", "@dismissable": "false", "@bounds": "[904,85][952,228]"}]}, {"@index": "3", "@text": "", "@resource-id": "com.alipay.mobile.antui:id/right_container_2", "@class": "android.widget.RelativeLayout", "@package": "com.eg.android.AlipayGphone", "@content-desc": "\u804a\u5929\u8bbe\u7f6e", "@checkable": "false", "@checked": "false", "@clickable": "true", "@enabled": "true", "@focusable": "true", "@focused": "false", "@scrollable": "false", "@long-clickable": "false", "@password": "false", "@selected": "false", "@editable": "false", "@accessibilityFocused": "false", "@dismissable": "false", "@bounds": "[952,85][1080,228]", "node": [{"@index": "0", "@text": "", "@resource-id": "com.alipay.mobile.antui:id/right_text", "@class": "android.widget.FrameLayout", "@package": "com.eg.android.AlipayGphone", "@content-desc": "", "@checkable": "false", "@checked": "false", "@clickable": "false", "@enabled": "true", "@focusable": "false", "@focused": "false", "@scrollable": "false", "@long-clickable": "false", "@password": "false", "@selected": "false", "@editable": "false", "@accessibilityFocused": "false", "@dismissable": "false", "@bounds": "[964,85][1033,228]", "node": {"@index": "0", "@text": "\ue620", "@resource-id": "", "@class": "android.widget.TextView", "@package": "com.eg.android.AlipayGphone", "@content-desc": " ", "@checkable": "false", "@checked": "false", "@clickable": "false", "@enabled": "true", "@focusable": "false", "@focused": "false", "@scrollable": "false", "@long-clickable": "false", "@password": "false", "@selected": "false", "@editable": "false", "@accessibilityFocused": "false", "@dismissable": "false", "@bounds": "[964,108][1033,204]"}}, {"@index": "1", "@text": "", "@resource-id": "", "@class": "android.view.View", "@package": "com.eg.android.AlipayGphone", "@content-desc": "", "@checkable": "false", "@checked": "false", "@clickable": "false", "@enabled": "true", "@focusable": "false", "@focused": "false", "@scrollable": "false", "@long-clickable": "false", "@password": "false", "@selected": "false", "@editable": "false", "@accessibilityFocused": "false", "@dismissable": "false", "@bounds": "[1033,85][1080,228]"}]}]}}}, {"@index": "1", "@text": "", "@resource-id": "com.alipay.mobile.chatapp:id/chat_msg_bg", "@class": "android.widget.RelativeLayout", "@package": "com.eg.android.AlipayGphone", "@content-desc": "", "@checkable": "false", "@checked": "false", "@clickable": "false", "@enabled": "true", "@focusable": "false", "@focused": "false", "@scrollable": "false", "@long-clickable": "false", "@password": "false", "@selected": "false", "@editable": "false", "@accessibilityFocused": "false", "@dismissable": "false", "@bounds": "[0,228][1080,2340]", "node": [{"@index": "0", "@text": "", "@resource-id": "com.alipay.mobile.chatapp:id/title_tips_container", "@class": "android.widget.FrameLayout", "@package": "com.eg.android.AlipayGphone", "@content-desc": "", "@checkable": "false", "@checked": "false", "@clickable": "false", "@enabled": "true", "@focusable": "false", "@focused": "false", "@scrollable": "false", "@long-clickable": "false", "@password": "false", "@selected": "false", "@editable": "false", "@accessibilityFocused": "false", "@dismissable": "false", "@bounds": "[0,228][1080,228]"}, {"@index": "1", "@text": "", "@resource-id": "com.alipay.mobile.chatapp:id/iv_bg", "@class": "android.widget.ImageView", "@package": "com.eg.android.AlipayGphone", "@content-desc": "", "@checkable": "false", "@checked": "false", "@clickable": "false", "@enabled": "true", "@focusable": "false", "@focused": "false", "@scrollable": "false", "@long-clickable": "false", "@password": "false", "@selected": "false", "@editable": "false", "@accessibilityFocused": "false", "@dismissable": "false", "@bounds": "[0,228][1080,2340]"}, {"@index": "2", "@text": "", "@resource-id": "com.alipay.mobile.chatapp:id/chat_msg_list", "@class": "android.widget.ListView", "@package": "com.eg.android.AlipayGphone", "@content-desc": "", "@checkable": "false", "@checked": "false", "@clickable": "false", "@enabled": "true", "@focusable": "true", "@focused": "false", "@scrollable": "false", "@long-clickable": "false", "@password": "false", "@selected": "false", "@editable": "false", "@accessibilityFocused": "false", "@dismissable": "false", "@bounds": "[0,228][1080,2196]", "node": [{"@index": "0", "@text": "", "@resource-id": "", "@class": "android.widget.FrameLayout", "@package": "com.eg.android.AlipayGphone", "@content-desc": "", "@checkable": "false", "@checked": "false", "@clickable": "true", "@enabled": "true", "@focusable": "false", "@focused": "false", "@scrollable": "false", "@long-clickable": "false", "@password": "false", "@selected": "false", "@editable": "false", "@accessibilityFocused": "false", "@dismissable": "false", "@bounds": "[0,228][1080,228]"}, {"@index": "1", "@text": "", "@resource-id": "", "@class": "android.widget.RelativeLayout", "@package": "com.eg.android.AlipayGphone", "@content-desc": "\u4e0b\u5348 12:55\u4f60\u53d1\u9001\u4e86 \u4e00\u6761\u8f6c\u8d26\u6d88\u606f", "@checkable": "false", "@checked": "false", "@clickable": "true", "@enabled": "true", "@focusable": "false", "@focused": "false", "@scrollable": "false", "@long-clickable": "false", "@password": "false", "@selected": "false", "@editable": "false", "@accessibilityFocused": "false", "@dismissable": "false", "@bounds": "[0,228][1080,960]", "node": {"@index": "0", "@text": "", "@resource-id": "", "@class": "android.widget.RelativeLayout", "@package": "com.eg.android.AlipayGphone", "@content-desc": "", "@checkable": "false", "@checked": "false", "@clickable": "false", "@enabled": "true", "@focusable": "false", "@focused": "false", "@scrollable": "false", "@long-clickable": "false", "@password": "false", "@selected": "false", "@editable": "false", "@accessibilityFocused": "false", "@dismissable": "false", "@bounds": "[0,228][1080,960]", "node": [{"@index": "0", "@text": "\u4e0b\u5348 12:55", "@resource-id": "com.alipay.mobile.chatapp:id/chat_msg_time", "@class": "android.widget.TextView", "@package": "com.eg.android.AlipayGphone", "@content-desc": "", "@checkable": "false", "@checked": "false", "@clickable": "false", "@enabled": "true", "@focusable": "false", "@focused": "false", "@scrollable": "false", "@long-clickable": "false", "@password": "false", "@selected": "false", "@editable": "false", "@accessibilityFocused": "false", "@dismissable": "false", "@bounds": "[434,264][646,330]"}, {"@index": "1", "@text": "", "@resource-id": "com.alipay.mobile.chatapp:id/chat_msg_layout", "@class": "android.widget.RelativeLayout", "@package": "com.eg.android.AlipayGphone", "@content-desc": "", "@checkable": "false", "@checked": "false", "@clickable": "false", "@enabled": "true", "@focusable": "false", "@focused": "false", "@scrollable": "false", "@long-clickable": "false", "@password": "false", "@selected": "false", "@editable": "false", "@accessibilityFocused": "false", "@dismissable": "false", "@bounds": "[0,366][1080,924]", "node": [{"@index": "0", "@text": "", "@resource-id": "com.alipay.mobile.chatapp:id/chat_msg_name", "@class": "android.widget.RelativeLayout", "@package": "com.eg.android.AlipayGphone", "@content-desc": "", "@checkable": "false", "@checked": "false", "@clickable": "false", "@enabled": "true", "@focusable": "false", "@focused": "false", "@scrollable": "false", "@long-clickable": "false", "@password": "false", "@selected": "false", "@editable": "false", "@accessibilityFocused": "false", "@dismissable": "false", "@bounds": "[903,366][903,366]"}, {"@index": "1", "@text": "", "@resource-id": "", "@class": "android.widget.RelativeLayout", "@package": "com.eg.android.AlipayGphone", "@content-desc": "", "@checkable": "false", "@checked": "false", "@clickable": "false", "@enabled": "true", "@focusable": "false", "@focused": "false", "@scrollable": "false", "@long-clickable": "false", "@password": "false", "@selected": "false", "@editable": "false", "@accessibilityFocused": "false", "@dismissable": "false", "@bounds": "[96,366][924,924]", "node": [{"@index": "0", "@text": "", "@resource-id": "com.alipay.mobile.chatapp:id/chat_msg_bubble_biz", "@class": "android.widget.RelativeLayout", "@package": "com.eg.android.AlipayGphone", "@content-desc": "\u4e0b\u5348 12:55\u4f60\u53d1\u9001\u4e86 \u4e00\u6761\u8f6c\u8d26\u6d88\u606f", "@checkable": "false", "@checked": "false", "@clickable": "true", "@enabled": "true", "@focusable": "true", "@focused": "false", "@scrollable": "false", "@long-clickable": "true", "@password": "false", "@selected": "false", "@editable": "false", "@accessibilityFocused": "false", "@dismissable": "false", "@bounds": "[186,366][924,655]", "node": [{"@index": "0", "@text": "", "@resource-id": "com.alipay.mobile.chatapp:id/chat_msg_biz_top", "@class": "android.widget.RelativeLayout", "@package": "com.eg.android.AlipayGphone", "@content-desc": "", "@checkable": "false", "@checked": "false", "@clickable": "false", "@enabled": "true", "@focusable": "false", "@focused": "false", "@scrollable": "false", "@long-clickable": "false", "@password": "false", "@selected": "false", "@editable": "false", "@accessibilityFocused": "false", "@dismissable": "false", "@bounds": "[186,366][924,568]", "node": [{"@index": "0", "@text": "", "@resource-id": "com.alipay.mobile.chatapp:id/biz_img", "@class": "android.widget.ImageView", "@package": "com.eg.android.AlipayGphone", "@content-desc": "", "@checkable": "false", "@checked": "false", "@clickable": "false", "@enabled": "true", "@focusable": "false", "@focused": "false", "@scrollable": "false", "@long-clickable": "false", "@password": "false", "@selected": "false", "@editable": "false", "@accessibilityFocused": "false", "@dismissable": "false", "@bounds": "[226,407][346,527]"}, {"@index": "1", "@text": "", "@resource-id": "", "@class": "android.widget.LinearLayout", "@package": "com.eg.android.AlipayGphone", "@content-desc": "", "@checkable": "false", "@checked": "false", "@clickable": "false", "@enabled": "true", "@focusable": "false", "@focused": "false", "@scrollable": "false", "@long-clickable": "false", "@password": "false", "@selected": "false", "@editable": "false", "@accessibilityFocused": "false", "@dismissable": "false", "@bounds": "[366,401][561,533]", "node": [{"@index": "0", "@text": "1.00\u5143", "@resource-id": "com.alipay.mobile.chatapp:id/biz_desc", "@class": "android.widget.TextView", "@package": "com.eg.android.AlipayGphone", "@content-desc": "", "@checkable": "false", "@checked": "false", "@clickable": "false", "@enabled": "true", "@focusable": "false", "@focused": "false", "@scrollable": "false", "@long-clickable": "false", "@password": "false", "@selected": "false", "@editable": "false", "@accessibilityFocused": "false", "@dismissable": "false", "@bounds": "[366,401][498,464]"}, {"@index": "1", "@text": "\u8f6c\u8d26\u7ed9\u839c\u84dd", "@resource-id": "com.alipay.mobile.chatapp:id/biz_title", "@class": "android.widget.TextView", "@package": "com.eg.android.AlipayGphone", "@content-desc": "", "@checkable": "false", "@checked": "false", "@clickable": "false", "@enabled": "true", "@focusable": "false", "@focused": "false", "@scrollable": "false", "@long-clickable": "false", "@password": "false", "@selected": "false", "@editable": "false", "@accessibilityFocused": "false", "@dismissable": "false", "@bounds": "[366,476][561,533]"}]}]}, {"@index": "1", "@text": "", "@resource-id": "com.alipay.mobile.chatapp:id/chat_msg_biz_bottom", "@class": "android.widget.RelativeLayout", "@package": "com.eg.android.AlipayGphone", "@content-desc": "", "@checkable": "false", "@checked": "false", "@clickable": "false", "@enabled": "true", "@focusable": "false", "@focused": "false", "@scrollable": "false", "@long-clickable": "false", "@password": "false", "@selected": "false", "@editable": "false", "@accessibilityFocused": "false", "@dismissable": "false", "@bounds": "[186,568][924,655]", "node": [{"@index": "0", "@text": "\u8f6c\u8d26", "@resource-id": "com.alipay.mobile.chatapp:id/biz_app_desc", "@class": "android.widget.TextView", "@package": "com.eg.android.AlipayGphone", "@content-desc": "", "@checkable": "false", "@checked": "false", "@clickable": "false", "@enabled": "true", "@focusable": "false", "@focused": "false", "@scrollable": "false", "@long-clickable": "false", "@password": "false", "@selected": "false", "@editable": "false", "@accessibilityFocused": "false", "@dismissable": "false", "@bounds": "[226,582][814,640]"}, {"@index": "1", "@text": "", "@resource-id": "com.alipay.mobile.chatapp:id/biz_app_icon", "@class": "android.widget.ImageView", "@package": "com.eg.android.AlipayGphone", "@content-desc": "", "@checkable": "false", "@checked": "false", "@clickable": "false", "@enabled": "true", "@focusable": "false", "@focused": "false", "@scrollable": "false", "@long-clickable": "false", "@password": "false", "@selected": "false", "@editable": "false", "@accessibilityFocused": "false", "@dismissable": "false", "@bounds": "[829,591][869,631]"}]}]}, {"@index": "1", "@text": "", "@resource-id": "com.alipay.mobile.chatapp:id/yuebao_extra", "@class": "android.widget.LinearLayout", "@package": "com.eg.android.AlipayGphone", "@content-desc": "", "@checkable": "false", "@checked": "false", "@clickable": "true", "@enabled": "true", "@focusable": "true", "@focused": "false", "@scrollable": "false", "@long-clickable": "true", "@password": "false", "@selected": "false", "@editable": "false", "@accessibilityFocused": "false", "@dismissable": "false", "@bounds": "[186,655][924,924]", "node": [{"@index": "0", "@text": "", "@resource-id": "", "@class": "android.widget.RelativeLayout", "@package": "com.eg.android.AlipayGphone", "@content-desc": "", "@checkable": "false", "@checked": "false", "@clickable": "false", "@enabled": "true", "@focusable": "false", "@focused": "false", "@scrollable": "false", "@long-clickable": "false", "@password": "false", "@selected": "false", "@editable": "false", "@accessibilityFocused": "false", "@dismissable": "false", "@bounds": "[231,691][879,748]", "node": {"@index": "0", "@text": "\u672c\u6b21\u8f6c\u8d26\u83b7\u5f97\u8f6c\u8f6c\u5361\u5956\u52b1", "@resource-id": "com.alipay.mobile.chatapp:id/yuebao_title", "@class": "android.widget.TextView", "@package": "com.eg.android.AlipayGphone", "@content-desc": "", "@checkable": "false", "@checked": "false", "@clickable": "false", "@enabled": "true", "@focusable": "false", "@focused": "false", "@scrollable": "false", "@long-clickable": "false", "@password": "false", "@selected": "false", "@editable": "false", "@accessibilityFocused": "false", "@dismissable": "false", "@bounds": "[324,691][786,748]"}}, {"@index": "1", "@text": "\u53bb\u5151\u7ea2\u5305", "@resource-id": "com.alipay.mobile.chatapp:id/yuebao_button", "@class": "android.widget.TextView", "@package": "com.eg.android.AlipayGphone", "@content-desc": "", "@checkable": "false", "@checked": "false", "@clickable": "false", "@enabled": "true", "@focusable": "false", "@focused": "false", "@scrollable": "false", "@long-clickable": "false", "@password": "false", "@selected": "false", "@editable": "false", "@accessibilityFocused": "false", "@dismissable": "false", "@bounds": "[333,772][777,864]"}]}]}, {"@index": "2", "@text": "", "@resource-id": "com.alipay.mobile.chatapp:id/chat_msg_avatar_layout", "@class": "android.widget.FrameLayout", "@package": "com.eg.android.AlipayGphone", "@content-desc": "", "@checkable": "false", "@checked": "false", "@clickable": "false", "@enabled": "true", "@focusable": "false", "@focused": "false", "@scrollable": "false", "@long-clickable": "false", "@password": "false", "@selected": "false", "@editable": "false", "@accessibilityFocused": "false", "@dismissable": "false", "@bounds": "[936,366][1056,486]", "node": [{"@index": "0", "@text": "", "@resource-id": "com.alipay.mobile.chatapp:id/chat_msg_avatar_cover", "@class": "android.widget.ImageView", "@package": "com.eg.android.AlipayGphone", "@content-desc": "", "@checkable": "false", "@checked": "false", "@clickable": "false", "@enabled": "true", "@focusable": "false", "@focused": "false", "@scrollable": "false", "@long-clickable": "false", "@password": "false", "@selected": "false", "@editable": "false", "@accessibilityFocused": "false", "@dismissable": "false", "@bounds": "[936,366][1056,486]"}, {"@index": "1", "@text": "", "@resource-id": "com.alipay.mobile.chatapp:id/chat_msg_avatar", "@class": "android.widget.ImageView", "@package": "com.eg.android.AlipayGphone", "@content-desc": "\u6770", "@checkable": "false", "@checked": "false", "@clickable": "true", "@enabled": "true", "@focusable": "true", "@focused": "false", "@scrollable": "false", "@long-clickable": "false", "@password": "false", "@selected": "false", "@editable": "false", "@accessibilityFocused": "false", "@dismissable": "false", "@bounds": "[936,366][1056,486]"}]}, {"@index": "3", "@text": "", "@resource-id": "com.alipay.mobile.chatapp:id/chat_msg_checkbox_fl", "@class": "android.widget.FrameLayout", "@package": "com.eg.android.AlipayGphone", "@content-desc": "", "@checkable": "false", "@checked": "false", "@clickable": "false", "@enabled": "true", "@focusable": "false", "@focused": "false", "@scrollable": "false", "@long-clickable": "false", "@password": "false", "@selected": "false", "@editable": "false", "@accessibilityFocused": "false", "@dismissable": "false", "@bounds": "[1080,366][1080,486]"}]}]}}, {"@index": "2", "@text": "", "@resource-id": "", "@class": "android.widget.RelativeLayout", "@package": "com.eg.android.AlipayGphone", "@content-desc": "\u4e0b\u5348 2:29\u4f60\u53d1\u9001\u4e86 \u4e00\u6761\u8f6c\u8d26\u6d88\u606f", "@checkable": "false", "@checked": "false", "@clickable": "true", "@enabled": "true", "@focusable": "false", "@focused": "false", "@scrollable": "false", "@long-clickable": "false", "@password": "false", "@selected": "false", "@editable": "false", "@accessibilityFocused": "false", "@dismissable": "false", "@bounds": "[0,960][1080,1423]", "node": {"@index": "0", "@text": "", "@resource-id": "", "@class": "android.widget.RelativeLayout", "@package": "com.eg.android.AlipayGphone", "@content-desc": "", "@checkable": "false", "@checked": "false", "@clickable": "false", "@enabled": "true", "@focusable": "false", "@focused": "false", "@scrollable": "false", "@long-clickable": "false", "@password": "false", "@selected": "false", "@editable": "false", "@accessibilityFocused": "false", "@dismissable": "false", "@bounds": "[0,960][1080,1423]", "node": [{"@index": "0", "@text": "\u4e0b\u5348 2:29", "@resource-id": "com.alipay.mobile.chatapp:id/chat_msg_time", "@class": "android.widget.TextView", "@package": "com.eg.android.AlipayGphone", "@content-desc": "", "@checkable": "false", "@checked": "false", "@clickable": "false", "@enabled": "true", "@focusable": "false", "@focused": "false", "@scrollable": "false", "@long-clickable": "false", "@password": "false", "@selected": "false", "@editable": "false", "@accessibilityFocused": "false", "@dismissable": "false", "@bounds": "[444,996][636,1062]"}, {"@index": "1", "@text": "", "@resource-id": "com.alipay.mobile.chatapp:id/chat_msg_layout", "@class": "android.widget.RelativeLayout", "@package": "com.eg.android.AlipayGphone", "@content-desc": "", "@checkable": "false", "@checked": "false", "@clickable": "false", "@enabled": "true", "@focusable": "false", "@focused": "false", "@scrollable": "false", "@long-clickable": "false", "@password": "false", "@selected": "false", "@editable": "false", "@accessibilityFocused": "false", "@dismissable": "false", "@bounds": "[0,1098][1080,1387]", "node": [{"@index": "0", "@text": "", "@resource-id": "com.alipay.mobile.chatapp:id/chat_msg_name", "@class": "android.widget.RelativeLayout", "@package": "com.eg.android.AlipayGphone", "@content-desc": "", "@checkable": "false", "@checked": "false", "@clickable": "false", "@enabled": "true", "@focusable": "false", "@focused": "false", "@scrollable": "false", "@long-clickable": "false", "@password": "false", "@selected": "false", "@editable": "false", "@accessibilityFocused": "false", "@dismissable": "false", "@bounds": "[903,1098][903,1098]"}, {"@index": "1", "@text": "", "@resource-id": "", "@class": "android.widget.RelativeLayout", "@package": "com.eg.android.AlipayGphone", "@content-desc": "", "@checkable": "false", "@checked": "false", "@clickable": "false", "@enabled": "true", "@focusable": "false", "@focused": "false", "@scrollable": "false", "@long-clickable": "false", "@password": "false", "@selected": "false", "@editable": "false", "@accessibilityFocused": "false", "@dismissable": "false", "@bounds": "[96,1098][924,1387]", "node": {"@index": "0", "@text": "", "@resource-id": "com.alipay.mobile.chatapp:id/chat_msg_bubble_biz", "@class": "android.widget.RelativeLayout", "@package": "com.eg.android.AlipayGphone", "@content-desc": "\u4e0b\u5348 2:29\u4f60\u53d1\u9001\u4e86 \u4e00\u6761\u8f6c\u8d26\u6d88\u606f", "@checkable": "false", "@checked": "false", "@clickable": "true", "@enabled": "true", "@focusable": "true", "@focused": "false", "@scrollable": "false", "@long-clickable": "true", "@password": "false", "@selected": "false", "@editable": "false", "@accessibilityFocused": "false", "@dismissable": "false", "@bounds": "[186,1098][924,1387]", "node": [{"@index": "0", "@text": "", "@resource-id": "com.alipay.mobile.chatapp:id/chat_msg_biz_top", "@class": "android.widget.RelativeLayout", "@package": "com.eg.android.AlipayGphone", "@content-desc": "", "@checkable": "false", "@checked": "false", "@clickable": "false", "@enabled": "true", "@focusable": "false", "@focused": "false", "@scrollable": "false", "@long-clickable": "false", "@password": "false", "@selected": "false", "@editable": "false", "@accessibilityFocused": "false", "@dismissable": "false", "@bounds": "[186,1098][924,1300]", "node": [{"@index": "0", "@text": "", "@resource-id": "com.alipay.mobile.chatapp:id/biz_img", "@class": "android.widget.ImageView", "@package": "com.eg.android.AlipayGphone", "@content-desc": "", "@checkable": "false", "@checked": "false", "@clickable": "false", "@enabled": "true", "@focusable": "false", "@focused": "false", "@scrollable": "false", "@long-clickable": "false", "@password": "false", "@selected": "false", "@editable": "false", "@accessibilityFocused": "false", "@dismissable": "false", "@bounds": "[226,1139][346,1259]"}, {"@index": "1", "@text": "", "@resource-id": "", "@class": "android.widget.LinearLayout", "@package": "com.eg.android.AlipayGphone", "@content-desc": "", "@checkable": "false", "@checked": "false", "@clickable": "false", "@enabled": "true", "@focusable": "false", "@focused": "false", "@scrollable": "false", "@long-clickable": "false", "@password": "false", "@selected": "false", "@editable": "false", "@accessibilityFocused": "false", "@dismissable": "false", "@bounds": "[366,1133][561,1265]", "node": [{"@index": "0", "@text": "1.00\u5143", "@resource-id": "com.alipay.mobile.chatapp:id/biz_desc", "@class": "android.widget.TextView", "@package": "com.eg.android.AlipayGphone", "@content-desc": "", "@checkable": "false", "@checked": "false", "@clickable": "false", "@enabled": "true", "@focusable": "false", "@focused": "false", "@scrollable": "false", "@long-clickable": "false", "@password": "false", "@selected": "false", "@editable": "false", "@accessibilityFocused": "false", "@dismissable": "false", "@bounds": "[366,1133][498,1196]"}, {"@index": "1", "@text": "\u8f6c\u8d26\u7ed9\u839c\u84dd", "@resource-id": "com.alipay.mobile.chatapp:id/biz_title", "@class": "android.widget.TextView", "@package": "com.eg.android.AlipayGphone", "@content-desc": "", "@checkable": "false", "@checked": "false", "@clickable": "false", "@enabled": "true", "@focusable": "false", "@focused": "false", "@scrollable": "false", "@long-clickable": "false", "@password": "false", "@selected": "false", "@editable": "false", "@accessibilityFocused": "false", "@dismissable": "false", "@bounds": "[366,1208][561,1265]"}]}]}, {"@index": "1", "@text": "", "@resource-id": "com.alipay.mobile.chatapp:id/chat_msg_biz_bottom", "@class": "android.widget.RelativeLayout", "@package": "com.eg.android.AlipayGphone", "@content-desc": "", "@checkable": "false", "@checked": "false", "@clickable": "false", "@enabled": "true", "@focusable": "false", "@focused": "false", "@scrollable": "false", "@long-clickable": "false", "@password": "false", "@selected": "false", "@editable": "false", "@accessibilityFocused": "false", "@dismissable": "false", "@bounds": "[186,1300][924,1387]", "node": [{"@index": "0", "@text": "\u8f6c\u8d26", "@resource-id": "com.alipay.mobile.chatapp:id/biz_app_desc", "@class": "android.widget.TextView", "@package": "com.eg.android.AlipayGphone", "@content-desc": "", "@checkable": "false", "@checked": "false", "@clickable": "false", "@enabled": "true", "@focusable": "false", "@focused": "false", "@scrollable": "false", "@long-clickable": "false", "@password": "false", "@selected": "false", "@editable": "false", "@accessibilityFocused": "false", "@dismissable": "false", "@bounds": "[226,1314][814,1372]"}, {"@index": "1", "@text": "", "@resource-id": "com.alipay.mobile.chatapp:id/biz_app_icon", "@class": "android.widget.ImageView", "@package": "com.eg.android.AlipayGphone", "@content-desc": "", "@checkable": "false", "@checked": "false", "@clickable": "false", "@enabled": "true", "@focusable": "false", "@focused": "false", "@scrollable": "false", "@long-clickable": "false", "@password": "false", "@selected": "false", "@editable": "false", "@accessibilityFocused": "false", "@dismissable": "false", "@bounds": "[829,1323][869,1363]"}]}]}}, {"@index": "2", "@text": "", "@resource-id": "com.alipay.mobile.chatapp:id/chat_msg_avatar_layout", "@class": "android.widget.FrameLayout", "@package": "com.eg.android.AlipayGphone", "@content-desc": "", "@checkable": "false", "@checked": "false", "@clickable": "false", "@enabled": "true", "@focusable": "false", "@focused": "false", "@scrollable": "false", "@long-clickable": "false", "@password": "false", "@selected": "false", "@editable": "false", "@accessibilityFocused": "false", "@dismissable": "false", "@bounds": "[936,1098][1056,1218]", "node": [{"@index": "0", "@text": "", "@resource-id": "com.alipay.mobile.chatapp:id/chat_msg_avatar_cover", "@class": "android.widget.ImageView", "@package": "com.eg.android.AlipayGphone", "@content-desc": "", "@checkable": "false", "@checked": "false", "@clickable": "false", "@enabled": "true", "@focusable": "false", "@focused": "false", "@scrollable": "false", "@long-clickable": "false", "@password": "false", "@selected": "false", "@editable": "false", "@accessibilityFocused": "false", "@dismissable": "false", "@bounds": "[936,1098][1056,1218]"}, {"@index": "1", "@text": "", "@resource-id": "com.alipay.mobile.chatapp:id/chat_msg_avatar", "@class": "android.widget.ImageView", "@package": "com.eg.android.AlipayGphone", "@content-desc": "\u6770", "@checkable": "false", "@checked": "false", "@clickable": "true", "@enabled": "true", "@focusable": "true", "@focused": "false", "@scrollable": "false", "@long-clickable": "false", "@password": "false", "@selected": "false", "@editable": "false", "@accessibilityFocused": "false", "@dismissable": "false", "@bounds": "[936,1098][1056,1218]"}]}, {"@index": "3", "@text": "", "@resource-id": "com.alipay.mobile.chatapp:id/chat_msg_checkbox_fl", "@class": "android.widget.FrameLayout", "@package": "com.eg.android.AlipayGphone", "@content-desc": "", "@checkable": "false", "@checked": "false", "@clickable": "false", "@enabled": "true", "@focusable": "false", "@focused": "false", "@scrollable": "false", "@long-clickable": "false", "@password": "false", "@selected": "false", "@editable": "false", "@accessibilityFocused": "false", "@dismissable": "false", "@bounds": "[1080,1098][1080,1218]"}]}]}}, {"@index": "3", "@text": "", "@resource-id": "", "@class": "android.widget.RelativeLayout", "@package": "com.eg.android.AlipayGphone", "@content-desc": "\u4e0b\u5348 2:29\u4f60\u53d1\u9001\u4e86 \u4e00\u6761\u6d88\u606f", "@checkable": "false", "@checked": "false", "@clickable": "false", "@enabled": "true", "@focusable": "false", "@focused": "false", "@scrollable": "false", "@long-clickable": "false", "@password": "false", "@selected": "false", "@editable": "false", "@accessibilityFocused": "false", "@dismissable": "false", "@bounds": "[0,1423][1080,1610]", "node": {"@index": "0", "@text": "", "@resource-id": "", "@class": "android.widget.RelativeLayout", "@package": "com.eg.android.AlipayGphone", "@content-desc": "", "@checkable": "false", "@checked": "false", "@clickable": "false", "@enabled": "true", "@focusable": "false", "@focused": "false", "@scrollable": "false", "@long-clickable": "false", "@password": "false", "@selected": "false", "@editable": "false", "@accessibilityFocused": "false", "@dismissable": "false", "@bounds": "[0,1423][1080,1610]", "node": {"@index": "0", "@text": "\u8f6c\u8d26\u6210\u529f\uff0c\u9a6c\u4e0a\u901a\u77e5TA", "@resource-id": "com.alipay.mobile.chatapp:id/sys_msg_tv", "@class": "android.widget.TextView", "@package": "com.eg.android.AlipayGphone", "@content-desc": "\u8f6c\u8d26\u6210\u529f\uff0c\u9a6c\u4e0a\u901a\u77e5TA", "@checkable": "false", "@checked": "false", "@clickable": "true", "@enabled": "true", "@focusable": "true", "@focused": "false", "@scrollable": "false", "@long-clickable": "true", "@password": "false", "@selected": "false", "@editable": "false", "@accessibilityFocused": "false", "@dismissable": "false", "@bounds": "[296,1423][784,1574]"}}}]}, {"@index": "3", "@text": "", "@resource-id": "com.alipay.mobile.chatapp:id/quick_menu_frame", "@class": "android.widget.FrameLayout", "@package": "com.eg.android.AlipayGphone", "@content-desc": "", "@checkable": "false", "@checked": "false", "@clickable": "false", "@enabled": "true", "@focusable": "false", "@focused": "false", "@scrollable": "false", "@long-clickable": "false", "@password": "false", "@selected": "false", "@editable": "false", "@accessibilityFocused": "false", "@dismissable": "false", "@bounds": "[0,2196][1080,2196]"}, {"@index": "4", "@text": "", "@resource-id": "com.alipay.mobile.chatapp:id/bottom_button_line", "@class": "android.view.View", "@package": "com.eg.android.AlipayGphone", "@content-desc": "", "@checkable": "false", "@checked": "false", "@clickable": "false", "@enabled": "true", "@focusable": "false", "@focused": "false", "@scrollable": "false", "@long-clickable": "false", "@password": "false", "@selected": "false", "@editable": "false", "@accessibilityFocused": "false", "@dismissable": "false", "@bounds": "[0,2196][1080,2197]"}, {"@index": "5", "@text": "", "@resource-id": "com.alipay.mobile.chatapp:id/bottom_frameLayout", "@class": "android.widget.FrameLayout", "@package": "com.eg.android.AlipayGphone", "@content-desc": "", "@checkable": "false", "@checked": "false", "@clickable": "false", "@enabled": "true", "@focusable": "false", "@focused": "false", "@scrollable": "false", "@long-clickable": "false", "@password": "false", "@selected": "false", "@editable": "false", "@accessibilityFocused": "false", "@dismissable": "false", "@bounds": "[0,2197][1080,2340]", "node": {"@index": "0", "@text": "", "@resource-id": "com.alipay.mobile.chatapp:id/bottom_msg_stage_layout", "@class": "android.widget.RelativeLayout", "@package": "com.eg.android.AlipayGphone", "@content-desc": "", "@checkable": "false", "@checked": "false", "@clickable": "false", "@enabled": "true", "@focusable": "false", "@focused": "false", "@scrollable": "false", "@long-clickable": "false", "@password": "false", "@selected": "false", "@editable": "false", "@accessibilityFocused": "false", "@dismissable": "false", "@bounds": "[0,2197][1080,2340]", "node": [{"@index": "0", "@text": "", "@resource-id": "com.alipay.mobile.chatapp:id/msg_bottom_layout", "@class": "android.widget.RelativeLayout", "@package": "com.eg.android.AlipayGphone", "@content-desc": "", "@checkable": "false", "@checked": "false", "@clickable": "false", "@enabled": "true", "@focusable": "false", "@focused": "false", "@scrollable": "false", "@long-clickable": "false", "@password": "false", "@selected": "false", "@editable": "false", "@accessibilityFocused": "false", "@dismissable": "false", "@bounds": "[0,2197][1080,2339]", "node": [{"@index": "0", "@text": "", "@resource-id": "com.alipay.mobile.chatapp:id/voiceSwitchBtn", "@class": "android.widget.ImageView", "@package": "com.eg.android.AlipayGphone", "@content-desc": "\u8bed\u97f3", "@checkable": "false", "@checked": "false", "@clickable": "true", "@enabled": "true", "@focusable": "true", "@focused": "false", "@scrollable": "false", "@long-clickable": "false", "@password": "false", "@selected": "false", "@editable": "false", "@accessibilityFocused": "false", "@dismissable": "false", "@bounds": "[36,2220][132,2316]"}, {"@index": "1", "@text": "", "@resource-id": "com.alipay.mobile.chatapp:id/chat_msg_inputbox_rl", "@class": "android.widget.RelativeLayout", "@package": "com.eg.android.AlipayGphone", "@content-desc": "", "@checkable": "false", "@checked": "false", "@clickable": "false", "@enabled": "true", "@focusable": "true", "@focused": "false", "@scrollable": "false", "@long-clickable": "false", "@password": "false", "@selected": "false", "@editable": "false", "@accessibilityFocused": "false", "@dismissable": "false", "@bounds": "[156,2218][912,2318]", "node": [{"@index": "0", "@text": "", "@resource-id": "com.alipay.mobile.chatapp:id/chat_msg_edit", "@class": "android.widget.EditText", "@package": "com.eg.android.AlipayGphone", "@content-desc": "", "@checkable": "false", "@checked": "false", "@clickable": "true", "@enabled": "true", "@focusable": "true", "@focused": "false", "@scrollable": "false", "@long-clickable": "true", "@password": "false", "@selected": "false", "@editable": "true", "@accessibilityFocused": "false", "@dismissable": "false", "@bounds": "[156,2218][708,2316]"}, {"@index": "1", "@text": "", "@resource-id": "com.alipay.mobile.chatapp:id/chat_quick_tr_btn", "@class": "android.widget.ImageView", "@package": "com.eg.android.AlipayGphone", "@content-desc": "\u8f6c\u8d26", "@checkable": "false", "@checked": "false", "@clickable": "true", "@enabled": "true", "@focusable": "true", "@focused": "false", "@scrollable": "false", "@long-clickable": "false", "@password": "false", "@selected": "false", "@editable": "false", "@accessibilityFocused": "false", "@dismissable": "false", "@bounds": "[708,2232][780,2304]"}, {"@index": "2", "@text": "", "@resource-id": "com.alipay.mobile.chatapp:id/chat_expression_ctr_btn", "@class": "android.widget.ImageView", "@package": "com.eg.android.AlipayGphone", "@content-desc": "\u8868\u60c5", "@checkable": "false", "@checked": "false", "@clickable": "true", "@enabled": "true", "@focusable": "true", "@focused": "false", "@scrollable": "false", "@long-clickable": "false", "@password": "false", "@selected": "false", "@editable": "false", "@accessibilityFocused": "false", "@dismissable": "false", "@bounds": "[780,2223][912,2313]"}, {"@index": "3", "@text": "", "@resource-id": "com.alipay.mobile.chatapp:id/chat_msg_edit_seprator", "@class": "android.view.View", "@package": "com.eg.android.AlipayGphone", "@content-desc": "", "@checkable": "false", "@checked": "false", "@clickable": "false", "@enabled": "true", "@focusable": "false", "@focused": "false", "@scrollable": "false", "@long-clickable": "false", "@password": "false", "@selected": "false", "@editable": "false", "@accessibilityFocused": "false", "@dismissable": "false", "@bounds": "[156,2316][912,2318]"}]}, {"@index": "2", "@text": "", "@resource-id": "com.alipay.mobile.chatapp:id/chat_stage_control_framelayout", "@class": "android.widget.RelativeLayout", "@package": "com.eg.android.AlipayGphone", "@content-desc": "", "@checkable": "false", "@checked": "false", "@clickable": "false", "@enabled": "true", "@focusable": "false", "@focused": "false", "@scrollable": "false", "@long-clickable": "false", "@password": "false", "@selected": "false", "@editable": "false", "@accessibilityFocused": "false", "@dismissable": "false", "@bounds": "[912,2215][1080,2320]", "node": {"@index": "0", "@text": "", "@resource-id": "com.alipay.mobile.chatapp:id/chat_stage_control_btn", "@class": "android.widget.ImageView", "@package": "com.eg.android.AlipayGphone", "@content-desc": "\u66f4\u591a", "@checkable": "false", "@checked": "false", "@clickable": "true", "@enabled": "true", "@focusable": "true", "@focused": "false", "@scrollable": "false", "@long-clickable": "false", "@password": "false", "@selected": "false", "@editable": "false", "@accessibilityFocused": "false", "@dismissable": "false", "@bounds": "[948,2219][1044,2315]"}}]}, {"@index": "1", "@text": "", "@resource-id": "com.alipay.mobile.chatapp:id/chat_msg_input_line_bottom", "@class": "android.view.View", "@package": "com.eg.android.AlipayGphone", "@content-desc": "", "@checkable": "false", "@checked": "false", "@clickable": "false", "@enabled": "true", "@focusable": "false", "@focused": "false", "@scrollable": "false", "@long-clickable": "false", "@password": "false", "@selected": "false", "@editable": "false", "@accessibilityFocused": "false", "@dismissable": "false", "@bounds": "[0,2339][1080,2340]"}]}}]}]}}}, {"@index": "1", "@text": "", "@resource-id": "android:id/statusBarBackground", "@class": "android.view.View", "@package": "com.eg.android.AlipayGphone", "@content-desc": "", "@checkable": "false", "@checked": "false", "@clickable": "false", "@enabled": "true", "@focusable": "false", "@focused": "false", "@scrollable": "false", "@long-clickable": "false", "@password": "false", "@selected": "false", "@editable": "false", "@accessibilityFocused": "false", "@dismissable": "false", "@bounds": "[0,0][1080,85]"}]}