{"@index": "0", "@text": "", "@resource-id": "", "@class": "android.widget.FrameLayout", "@package": "com.eg.android.AlipayGphone", "@content-desc": "", "@checkable": "false", "@checked": "false", "@clickable": "false", "@enabled": "true", "@focusable": "false", "@focused": "false", "@scrollable": "false", "@long-clickable": "false", "@password": "false", "@selected": "false", "@editable": "false", "@accessibilityFocused": "false", "@dismissable": "false", "@bounds": "[0,0][1080,2244]", "node": {"@index": "0", "@text": "", "@resource-id": "", "@class": "android.widget.LinearLayout", "@package": "com.eg.android.AlipayGphone", "@content-desc": "", "@checkable": "false", "@checked": "false", "@clickable": "false", "@enabled": "true", "@focusable": "false", "@focused": "false", "@scrollable": "false", "@long-clickable": "false", "@password": "false", "@selected": "false", "@editable": "false", "@accessibilityFocused": "false", "@dismissable": "false", "@bounds": "[0,0][1080,2130]", "node": {"@index": "0", "@text": "", "@resource-id": "android:id/content", "@class": "android.widget.FrameLayout", "@package": "com.eg.android.AlipayGphone", "@content-desc": "", "@checkable": "false", "@checked": "false", "@clickable": "false", "@enabled": "true", "@focusable": "false", "@focused": "false", "@scrollable": "false", "@long-clickable": "false", "@password": "false", "@selected": "false", "@editable": "false", "@accessibilityFocused": "false", "@dismissable": "false", "@bounds": "[0,81][1080,2130]", "node": {"@index": "0", "@text": "", "@resource-id": "", "@class": "android.widget.RelativeLayout", "@package": "com.eg.android.AlipayGphone", "@content-desc": "", "@checkable": "false", "@checked": "false", "@clickable": "false", "@enabled": "true", "@focusable": "false", "@focused": "false", "@scrollable": "false", "@long-clickable": "false", "@password": "false", "@selected": "false", "@editable": "false", "@accessibilityFocused": "false", "@dismissable": "false", "@bounds": "[0,81][1080,2130]", "node": [{"@index": "0", "@text": "", "@resource-id": "com.alipay.android.phone.mobilecommon.verifyidentity:id/dynamic_root", "@class": "android.widget.RelativeLayout", "@package": "com.eg.android.AlipayGphone", "@content-desc": "", "@checkable": "false", "@checked": "false", "@clickable": "false", "@enabled": "true", "@focusable": "false", "@focused": "false", "@scrollable": "false", "@long-clickable": "false", "@password": "false", "@selected": "false", "@editable": "false", "@accessibilityFocused": "false", "@dismissable": "false", "@bounds": "[0,81][1080,2130]", "node": {"@index": "0", "@text": "", "@resource-id": "", "@class": "android.widget.FrameLayout", "@package": "com.eg.android.AlipayGphone", "@content-desc": "", "@checkable": "false", "@checked": "false", "@clickable": "false", "@enabled": "true", "@focusable": "false", "@focused": "false", "@scrollable": "false", "@long-clickable": "false", "@password": "false", "@selected": "false", "@editable": "false", "@accessibilityFocused": "false", "@dismissable": "false", "@bounds": "[0,81][1080,2130]", "node": {"@index": "0", "@text": "", "@resource-id": "", "@class": "android.widget.FrameLayout", "@package": "com.eg.android.AlipayGphone", "@content-desc": "", "@checkable": "false", "@checked": "false", "@clickable": "false", "@enabled": "true", "@focusable": "false", "@focused": "false", "@scrollable": "false", "@long-clickable": "false", "@password": "false", "@selected": "false", "@editable": "false", "@accessibilityFocused": "false", "@dismissable": "false", "@bounds": "[0,81][1080,2130]", "node": {"@index": "0", "@text": "", "@resource-id": "", "@class": "android.widget.FrameLayout", "@package": "com.eg.android.AlipayGphone", "@content-desc": "", "@checkable": "false", "@checked": "false", "@clickable": "false", "@enabled": "true", "@focusable": "false", "@focused": "false", "@scrollable": "false", "@long-clickable": "false", "@password": "false", "@selected": "false", "@editable": "false", "@accessibilityFocused": "false", "@dismissable": "false", "@bounds": "[0,81][1080,2130]", "node": [{"@index": "0", "@text": "", "@resource-id": "", "@class": "android.widget.FrameLayout", "@package": "com.eg.android.AlipayGphone", "@content-desc": "", "@checkable": "false", "@checked": "false", "@clickable": "false", "@enabled": "true", "@focusable": "false", "@focused": "false", "@scrollable": "false", "@long-clickable": "false", "@password": "false", "@selected": "false", "@editable": "false", "@accessibilityFocused": "false", "@dismissable": "false", "@bounds": "[0,81][1080,225]", "node": {"@index": "0", "@text": "", "@resource-id": "", "@class": "android.widget.FrameLayout", "@package": "com.eg.android.AlipayGphone", "@content-desc": "", "@checkable": "false", "@checked": "false", "@clickable": "false", "@enabled": "true", "@focusable": "false", "@focused": "false", "@scrollable": "false", "@long-clickable": "false", "@password": "false", "@selected": "false", "@editable": "false", "@accessibilityFocused": "false", "@dismissable": "false", "@bounds": "[0,81][1080,224]", "node": {"@index": "0", "@text": "", "@resource-id": "", "@class": "android.widget.FrameLayout", "@package": "com.eg.android.AlipayGphone", "@content-desc": "", "@checkable": "false", "@checked": "false", "@clickable": "false", "@enabled": "true", "@focusable": "false", "@focused": "false", "@scrollable": "false", "@long-clickable": "false", "@password": "false", "@selected": "false", "@editable": "false", "@accessibilityFocused": "false", "@dismissable": "false", "@bounds": "[0,81][1080,224]", "node": [{"@index": "0", "@text": "", "@resource-id": "", "@class": "android.widget.FrameLayout", "@package": "com.eg.android.AlipayGphone", "@content-desc": "", "@checkable": "false", "@checked": "false", "@clickable": "true", "@enabled": "true", "@focusable": "true", "@focused": "false", "@scrollable": "false", "@long-clickable": "false", "@password": "false", "@selected": "false", "@editable": "false", "@accessibilityFocused": "false", "@dismissable": "false", "@bounds": "[0,81][144,224]", "node": {"@index": "0", "@text": "", "@resource-id": "", "@class": "android.widget.ImageView", "@package": "com.eg.android.AlipayGphone", "@content-desc": "\u8fd4\u56de", "@checkable": "false", "@checked": "false", "@clickable": "false", "@enabled": "true", "@focusable": "false", "@focused": "false", "@scrollable": "false", "@long-clickable": "false", "@password": "false", "@selected": "false", "@editable": "false", "@accessibilityFocused": "false", "@dismissable": "false", "@bounds": "[36,117][108,189]"}}, {"@index": "1", "@text": "\u8bbe\u7f6e\u652f\u4ed8\u5bc6\u7801", "@resource-id": "", "@class": "android.widget.TextView", "@package": "com.eg.android.AlipayGphone", "@content-desc": "", "@checkable": "false", "@checked": "false", "@clickable": "false", "@enabled": "true", "@focusable": "false", "@focused": "false", "@scrollable": "false", "@long-clickable": "false", "@password": "false", "@selected": "false", "@editable": "false", "@accessibilityFocused": "false", "@dismissable": "false", "@bounds": "[181,120][1080,185]"}]}}}, {"@index": "1", "@text": "", "@resource-id": "", "@class": "android.widget.ScrollView", "@package": "com.eg.android.AlipayGphone", "@content-desc": "", "@checkable": "false", "@checked": "false", "@clickable": "false", "@enabled": "true", "@focusable": "true", "@focused": "false", "@scrollable": "false", "@long-clickable": "false", "@password": "false", "@selected": "false", "@editable": "false", "@accessibilityFocused": "false", "@dismissable": "false", "@bounds": "[0,225][1080,2130]", "node": {"@index": "0", "@text": "", "@resource-id": "", "@class": "android.widget.FrameLayout", "@package": "com.eg.android.AlipayGphone", "@content-desc": "", "@checkable": "false", "@checked": "false", "@clickable": "false", "@enabled": "true", "@focusable": "false", "@focused": "false", "@scrollable": "false", "@long-clickable": "false", "@password": "false", "@selected": "false", "@editable": "false", "@accessibilityFocused": "false", "@dismissable": "false", "@bounds": "[0,225][1080,772]", "node": [{"@index": "0", "@text": "", "@resource-id": "", "@class": "android.widget.FrameLayout", "@package": "com.eg.android.AlipayGphone", "@content-desc": "", "@checkable": "false", "@checked": "false", "@clickable": "false", "@enabled": "true", "@focusable": "false", "@focused": "false", "@scrollable": "false", "@long-clickable": "false", "@password": "false", "@selected": "false", "@editable": "false", "@accessibilityFocused": "false", "@dismissable": "false", "@bounds": "[45,270][1035,382]", "node": {"@index": "0", "@text": "\u8bbe\u7f6e\u652f\u4ed8\u5bc6\u7801\uff0c\u7528\u4e8e\u652f\u4ed8\u5b9d\u4ed8\u6b3e \u5efa\u8bae\u52ff\u4e0e\u94f6\u884c\u5361\u5bc6\u7801\u76f8\u540c", "@resource-id": "", "@class": "android.widget.TextView", "@package": "com.eg.android.AlipayGphone", "@content-desc": "", "@checkable": "false", "@checked": "false", "@clickable": "false", "@enabled": "true", "@focusable": "false", "@focused": "false", "@scrollable": "false", "@long-clickable": "false", "@password": "false", "@selected": "false", "@editable": "false", "@accessibilityFocused": "false", "@dismissable": "false", "@bounds": "[45,270][1035,382]"}}, {"@index": "1", "@text": "", "@resource-id": "", "@class": "android.widget.FrameLayout", "@package": "com.eg.android.AlipayGphone", "@content-desc": "", "@checkable": "false", "@checked": "false", "@clickable": "false", "@enabled": "true", "@focusable": "false", "@focused": "false", "@scrollable": "false", "@long-clickable": "false", "@password": "false", "@selected": "false", "@editable": "false", "@accessibilityFocused": "false", "@dismissable": "false", "@bounds": "[45,382][1035,613]", "node": {"@index": "0", "@text": "", "@resource-id": "", "@class": "android.widget.FrameLayout", "@package": "com.eg.android.AlipayGphone", "@content-desc": "", "@checkable": "false", "@checked": "false", "@clickable": "false", "@enabled": "true", "@focusable": "false", "@focused": "false", "@scrollable": "false", "@long-clickable": "false", "@password": "false", "@selected": "false", "@editable": "false", "@accessibilityFocused": "false", "@dismissable": "false", "@bounds": "[45,427][1035,568]", "node": {"@index": "0", "@text": "", "@resource-id": "", "@class": "android.widget.LinearLayout", "@package": "com.eg.android.AlipayGphone", "@content-desc": "", "@checkable": "false", "@checked": "false", "@clickable": "false", "@enabled": "true", "@focusable": "false", "@focused": "false", "@scrollable": "false", "@long-clickable": "false", "@password": "false", "@selected": "false", "@editable": "false", "@accessibilityFocused": "false", "@dismissable": "false", "@bounds": "[45,427][1035,568]", "node": {"@index": "0", "@text": "", "@resource-id": "com.alipay.android.phone.mobilecommon.verifyidentity:id/paypwd_layout", "@class": "android.widget.LinearLayout", "@package": "com.eg.android.AlipayGphone", "@content-desc": "", "@checkable": "false", "@checked": "false", "@clickable": "false", "@enabled": "true", "@focusable": "false", "@focused": "false", "@scrollable": "false", "@long-clickable": "false", "@password": "false", "@selected": "false", "@editable": "false", "@accessibilityFocused": "false", "@dismissable": "false", "@bounds": "[45,427][1035,565]", "node": {"@index": "0", "@text": "", "@resource-id": "", "@class": "android.widget.LinearLayout", "@package": "com.eg.android.AlipayGphone", "@content-desc": "", "@checkable": "false", "@checked": "false", "@clickable": "false", "@enabled": "true", "@focusable": "false", "@focused": "false", "@scrollable": "false", "@long-clickable": "false", "@password": "false", "@selected": "false", "@editable": "false", "@accessibilityFocused": "false", "@dismissable": "false", "@bounds": "[45,427][1035,565]", "node": {"@index": "0", "@text": "", "@resource-id": "com.alipay.android.phone.safepaybase:id/spwd_input", "@class": "android.widget.LinearLayout", "@package": "com.eg.android.AlipayGphone", "@content-desc": "", "@checkable": "false", "@checked": "false", "@clickable": "false", "@enabled": "true", "@focusable": "false", "@focused": "false", "@scrollable": "false", "@long-clickable": "false", "@password": "false", "@selected": "false", "@editable": "false", "@accessibilityFocused": "false", "@dismissable": "false", "@bounds": "[45,427][1035,565]", "node": {"@index": "0", "@text": "", "@resource-id": "", "@class": "android.widget.LinearLayout", "@package": "com.eg.android.AlipayGphone", "@content-desc": "", "@checkable": "false", "@checked": "false", "@clickable": "false", "@enabled": "true", "@focusable": "false", "@focused": "false", "@scrollable": "false", "@long-clickable": "false", "@password": "false", "@selected": "false", "@editable": "false", "@accessibilityFocused": "false", "@dismissable": "false", "@bounds": "[45,427][1035,565]", "node": {"@index": "0", "@text": "", "@resource-id": "com.alipay.android.phone.safepaybase:id/simplePwdLayout", "@class": "android.widget.RelativeLayout", "@package": "com.eg.android.AlipayGphone", "@content-desc": "", "@checkable": "false", "@checked": "false", "@clickable": "false", "@enabled": "true", "@focusable": "true", "@focused": "false", "@scrollable": "false", "@long-clickable": "false", "@password": "false", "@selected": "false", "@editable": "false", "@accessibilityFocused": "false", "@dismissable": "false", "@bounds": "[45,427][1035,565]", "node": {"@index": "0", "@text": "", "@resource-id": "com.alipay.android.phone.safepaybase:id/mini_linSimplePwdComponent", "@class": "android.widget.LinearLayout", "@package": "com.eg.android.AlipayGphone", "@content-desc": "", "@checkable": "false", "@checked": "false", "@clickable": "true", "@enabled": "true", "@focusable": "true", "@focused": "false", "@scrollable": "false", "@long-clickable": "false", "@password": "false", "@selected": "false", "@editable": "false", "@accessibilityFocused": "false", "@dismissable": "false", "@bounds": "[45,427][1035,565]"}}}}}}}}}, {"@index": "2", "@text": "", "@resource-id": "", "@class": "android.widget.FrameLayout", "@package": "com.eg.android.AlipayGphone", "@content-desc": "", "@checkable": "false", "@checked": "false", "@clickable": "false", "@enabled": "true", "@focusable": "false", "@focused": "false", "@scrollable": "false", "@long-clickable": "false", "@password": "false", "@selected": "false", "@editable": "false", "@accessibilityFocused": "false", "@dismissable": "false", "@bounds": "[45,613][1035,715]", "node": {"@index": "0", "@text": "\u4e24\u6b21\u8f93\u5165\u4e0d\u4e00\u81f4\uff0c\u8bf7\u91cd\u65b0\u8f93\u5165", "@resource-id": "", "@class": "android.widget.TextView", "@package": "com.eg.android.AlipayGphone", "@content-desc": "", "@checkable": "false", "@checked": "false", "@clickable": "false", "@enabled": "true", "@focusable": "false", "@focused": "false", "@scrollable": "false", "@long-clickable": "false", "@password": "false", "@selected": "false", "@editable": "false", "@accessibilityFocused": "false", "@dismissable": "false", "@bounds": "[267,613][813,670]"}}, {"@index": "3", "@text": "\u5bc6\u7801\u4e0d\u80fd\u4e3a\u8fde\u7eed\u3001\u91cd\u590d\u6570\u5b57\u6216\u8005\u4f60\u7684\u751f\u65e5", "@resource-id": "", "@class": "android.widget.TextView", "@package": "com.eg.android.AlipayGphone", "@content-desc": "", "@checkable": "false", "@checked": "false", "@clickable": "false", "@enabled": "true", "@focusable": "false", "@focused": "false", "@scrollable": "false", "@long-clickable": "false", "@password": "false", "@selected": "false", "@editable": "false", "@accessibilityFocused": "false", "@dismissable": "false", "@bounds": "[60,715][1035,772]"}]}}]}}}}, {"@index": "1", "@text": "", "@resource-id": "com.alipay.android.phone.mobilecommon.verifyidentity:id/keyboard_layout", "@class": "android.widget.LinearLayout", "@package": "com.eg.android.AlipayGphone", "@content-desc": "", "@checkable": "false", "@checked": "false", "@clickable": "false", "@enabled": "true", "@focusable": "false", "@focused": "false", "@scrollable": "false", "@long-clickable": "false", "@password": "false", "@selected": "false", "@editable": "false", "@accessibilityFocused": "false", "@dismissable": "false", "@bounds": "[0,1485][1080,2130]", "node": {"@index": "0", "@text": "", "@resource-id": "", "@class": "android.widget.LinearLayout", "@package": "com.eg.android.AlipayGphone", "@content-desc": "", "@checkable": "false", "@checked": "false", "@clickable": "false", "@enabled": "true", "@focusable": "false", "@focused": "false", "@scrollable": "false", "@long-clickable": "false", "@password": "false", "@selected": "false", "@editable": "false", "@accessibilityFocused": "false", "@dismissable": "false", "@bounds": "[0,1485][1080,2130]", "node": {"@index": "0", "@text": "", "@resource-id": "com.alipay.android.phone.safepaybase:id/ll_key_area_num", "@class": "android.widget.LinearLayout", "@package": "com.eg.android.AlipayGphone", "@content-desc": "", "@checkable": "false", "@checked": "false", "@clickable": "true", "@enabled": "true", "@focusable": "true", "@focused": "false", "@scrollable": "false", "@long-clickable": "false", "@password": "false", "@selected": "false", "@editable": "false", "@accessibilityFocused": "false", "@dismissable": "false", "@bounds": "[0,1485][1080,2130]", "node": [{"@index": "0", "@text": "", "@resource-id": "com.alipay.android.phone.safepaybase:id/row1_frame_num", "@class": "android.widget.LinearLayout", "@package": "com.eg.android.AlipayGphone", "@content-desc": "", "@checkable": "false", "@checked": "false", "@clickable": "false", "@enabled": "true", "@focusable": "false", "@focused": "false", "@scrollable": "false", "@long-clickable": "false", "@password": "false", "@selected": "false", "@editable": "false", "@accessibilityFocused": "false", "@dismissable": "false", "@bounds": "[0,1486][1080,1646]", "node": [{"@index": "0", "@text": "1", "@resource-id": "com.alipay.android.phone.safepaybase:id/key_num_1", "@class": "android.widget.TextView", "@package": "com.eg.android.AlipayGphone", "@content-desc": "", "@checkable": "false", "@checked": "false", "@clickable": "true", "@enabled": "true", "@focusable": "true", "@focused": "false", "@scrollable": "false", "@long-clickable": "false", "@password": "false", "@selected": "false", "@editable": "false", "@accessibilityFocused": "false", "@dismissable": "false", "@bounds": "[0,1486][359,1646]"}, {"@index": "1", "@text": "2", "@resource-id": "com.alipay.android.phone.safepaybase:id/key_num_2", "@class": "android.widget.TextView", "@package": "com.eg.android.AlipayGphone", "@content-desc": "", "@checkable": "false", "@checked": "false", "@clickable": "true", "@enabled": "true", "@focusable": "true", "@focused": "false", "@scrollable": "false", "@long-clickable": "false", "@password": "false", "@selected": "false", "@editable": "false", "@accessibilityFocused": "false", "@dismissable": "false", "@bounds": "[360,1486][719,1646]"}, {"@index": "2", "@text": "3", "@resource-id": "com.alipay.android.phone.safepaybase:id/key_num_3", "@class": "android.widget.TextView", "@package": "com.eg.android.AlipayGphone", "@content-desc": "", "@checkable": "false", "@checked": "false", "@clickable": "true", "@enabled": "true", "@focusable": "true", "@focused": "false", "@scrollable": "false", "@long-clickable": "false", "@password": "false", "@selected": "false", "@editable": "false", "@accessibilityFocused": "false", "@dismissable": "false", "@bounds": "[720,1486][1080,1646]"}]}, {"@index": "1", "@text": "", "@resource-id": "com.alipay.android.phone.safepaybase:id/row2_frame_num", "@class": "android.widget.LinearLayout", "@package": "com.eg.android.AlipayGphone", "@content-desc": "", "@checkable": "false", "@checked": "false", "@clickable": "false", "@enabled": "true", "@focusable": "false", "@focused": "false", "@scrollable": "false", "@long-clickable": "false", "@password": "false", "@selected": "false", "@editable": "false", "@accessibilityFocused": "false", "@dismissable": "false", "@bounds": "[0,1647][1080,1807]", "node": [{"@index": "0", "@text": "4", "@resource-id": "com.alipay.android.phone.safepaybase:id/key_4", "@class": "android.widget.TextView", "@package": "com.eg.android.AlipayGphone", "@content-desc": "", "@checkable": "false", "@checked": "false", "@clickable": "true", "@enabled": "true", "@focusable": "true", "@focused": "false", "@scrollable": "false", "@long-clickable": "false", "@password": "false", "@selected": "false", "@editable": "false", "@accessibilityFocused": "false", "@dismissable": "false", "@bounds": "[0,1647][359,1807]"}, {"@index": "1", "@text": "5", "@resource-id": "com.alipay.android.phone.safepaybase:id/key_num_5", "@class": "android.widget.TextView", "@package": "com.eg.android.AlipayGphone", "@content-desc": "", "@checkable": "false", "@checked": "false", "@clickable": "true", "@enabled": "true", "@focusable": "true", "@focused": "false", "@scrollable": "false", "@long-clickable": "false", "@password": "false", "@selected": "false", "@editable": "false", "@accessibilityFocused": "false", "@dismissable": "false", "@bounds": "[360,1647][719,1807]"}, {"@index": "2", "@text": "6", "@resource-id": "com.alipay.android.phone.safepaybase:id/key_num_6", "@class": "android.widget.TextView", "@package": "com.eg.android.AlipayGphone", "@content-desc": "", "@checkable": "false", "@checked": "false", "@clickable": "true", "@enabled": "true", "@focusable": "true", "@focused": "false", "@scrollable": "false", "@long-clickable": "false", "@password": "false", "@selected": "false", "@editable": "false", "@accessibilityFocused": "false", "@dismissable": "false", "@bounds": "[720,1647][1080,1807]"}]}, {"@index": "2", "@text": "", "@resource-id": "com.alipay.android.phone.safepaybase:id/row3_frame_num", "@class": "android.widget.LinearLayout", "@package": "com.eg.android.AlipayGphone", "@content-desc": "", "@checkable": "false", "@checked": "false", "@clickable": "false", "@enabled": "true", "@focusable": "false", "@focused": "false", "@scrollable": "false", "@long-clickable": "false", "@password": "false", "@selected": "false", "@editable": "false", "@accessibilityFocused": "false", "@dismissable": "false", "@bounds": "[0,1808][1080,1968]", "node": [{"@index": "0", "@text": "7", "@resource-id": "com.alipay.android.phone.safepaybase:id/key_num_7", "@class": "android.widget.TextView", "@package": "com.eg.android.AlipayGphone", "@content-desc": "", "@checkable": "false", "@checked": "false", "@clickable": "true", "@enabled": "true", "@focusable": "true", "@focused": "false", "@scrollable": "false", "@long-clickable": "false", "@password": "false", "@selected": "false", "@editable": "false", "@accessibilityFocused": "false", "@dismissable": "false", "@bounds": "[0,1808][359,1968]"}, {"@index": "1", "@text": "8", "@resource-id": "com.alipay.android.phone.safepaybase:id/key_num_8", "@class": "android.widget.TextView", "@package": "com.eg.android.AlipayGphone", "@content-desc": "", "@checkable": "false", "@checked": "false", "@clickable": "true", "@enabled": "true", "@focusable": "true", "@focused": "false", "@scrollable": "false", "@long-clickable": "false", "@password": "false", "@selected": "false", "@editable": "false", "@accessibilityFocused": "false", "@dismissable": "false", "@bounds": "[360,1808][719,1968]"}, {"@index": "2", "@text": "9", "@resource-id": "com.alipay.android.phone.safepaybase:id/key_num_9", "@class": "android.widget.TextView", "@package": "com.eg.android.AlipayGphone", "@content-desc": "", "@checkable": "false", "@checked": "false", "@clickable": "true", "@enabled": "true", "@focusable": "true", "@focused": "false", "@scrollable": "false", "@long-clickable": "false", "@password": "false", "@selected": "false", "@editable": "false", "@accessibilityFocused": "false", "@dismissable": "false", "@bounds": "[720,1808][1080,1968]"}]}, {"@index": "3", "@text": "", "@resource-id": "com.alipay.android.phone.safepaybase:id/row4_frame_num", "@class": "android.widget.LinearLayout", "@package": "com.eg.android.AlipayGphone", "@content-desc": "", "@checkable": "false", "@checked": "false", "@clickable": "false", "@enabled": "true", "@focusable": "false", "@focused": "false", "@scrollable": "false", "@long-clickable": "false", "@password": "false", "@selected": "false", "@editable": "false", "@accessibilityFocused": "false", "@dismissable": "false", "@bounds": "[0,1969][1080,2129]", "node": [{"@index": "0", "@text": "", "@resource-id": "com.alipay.android.phone.safepaybase:id/key_num_dymic", "@class": "android.widget.TextView", "@package": "com.eg.android.AlipayGphone", "@content-desc": "", "@checkable": "false", "@checked": "false", "@clickable": "true", "@enabled": "true", "@focusable": "true", "@focused": "false", "@scrollable": "false", "@long-clickable": "false", "@password": "false", "@selected": "false", "@editable": "false", "@accessibilityFocused": "false", "@dismissable": "false", "@bounds": "[0,1969][359,2129]"}, {"@index": "1", "@text": "0", "@resource-id": "com.alipay.android.phone.safepaybase:id/key_num_0", "@class": "android.widget.TextView", "@package": "com.eg.android.AlipayGphone", "@content-desc": "", "@checkable": "false", "@checked": "false", "@clickable": "true", "@enabled": "true", "@focusable": "true", "@focused": "false", "@scrollable": "false", "@long-clickable": "false", "@password": "false", "@selected": "false", "@editable": "false", "@accessibilityFocused": "false", "@dismissable": "false", "@bounds": "[360,1969][719,2129]"}, {"@index": "2", "@text": "", "@resource-id": "com.alipay.android.phone.safepaybase:id/key_num_del1", "@class": "android.widget.FrameLayout", "@package": "com.eg.android.AlipayGphone", "@content-desc": "", "@checkable": "false", "@checked": "false", "@clickable": "true", "@enabled": "true", "@focusable": "true", "@focused": "false", "@scrollable": "false", "@long-clickable": "false", "@password": "false", "@selected": "false", "@editable": "false", "@accessibilityFocused": "false", "@dismissable": "false", "@bounds": "[720,1969][1080,2129]"}]}]}}}]}}}}